Metadata-Version: 1.0
Name: ml-distributions
Version: 1.0
Summary: Gaussian & Binomial distributions
Home-page: UNKNOWN
Author: Shivam Agarwal
Author-email: UNKNOWN
License: UNKNOWN
Platform: UNKNOWN
